{
  "schema_version": 1,
  "last_updated": "2026-04-13T04:06:10Z",
  "rolling_window_days": 30,
  "categories": {
    "performance": {
      "merged": 8,
      "closed": 9,
      "acceptance_rate": 0.47,
      "status": "normal",
      "last_evaluated": "2026-04-07T03:57:21Z"
    },
    "security": {
      "merged": 21,
      "closed": 29,
      "acceptance_rate": 0.42,
      "status": "normal",
      "last_evaluated": "2026-04-07T03:57:21Z"
    },
    "a11y": {
      "merged": 34,
      "closed": 21,
      "acceptance_rate": 0.62,
      "status": "normal",
      "last_evaluated": "2026-04-07T03:57:21Z"
    },
    "operator": {
      "merged": 11,
      "closed": 130,
      "acceptance_rate": 0.08,
      "status": "blocked",
      "last_evaluated": "2026-04-13T04:06:10Z"
    },
    "sre": {
      "merged": 2,
      "closed": 21,
      "acceptance_rate": 0.09,
      "status": "blocked",
      "last_evaluated": "2026-04-08T03:58:11Z"
    },
    "features": {
      "merged": 3,
      "closed": 8,
      "acceptance_rate": 0.27,
      "status": "normal",
      "last_evaluated": "2026-04-08T03:58:11Z"
    },
    "resilience": {
      "merged": 37,
      "closed": 53,
      "acceptance_rate": 0.41,
      "status": "normal",
      "last_evaluated": "2026-04-08T03:58:11Z"
    },
    "consistency": {
      "merged": 15,
      "closed": 18,
      "acceptance_rate": 0.45,
      "status": "normal",
      "last_evaluated": "2026-04-05T03:59:32Z"
    }
  },
  "weekly_insights": {
    "best_pr_size": "S",
    "size_acceptance": {},
    "type_acceptance": {},
    "common_rejection_reasons": [],
    "best_change_type": "bug_fix",
    "last_report_date": "2026-05-03"
  },
  "cncf_insights": {
    "last_scan_date": "2026-05-06",
    "suggested_checks": [
      {
        "pattern": "navigation_ux",
        "count": 16,
        "added": "2026-05-06",
        "priority": "medium"
      },
      {
        "pattern": "data_viz",
        "count": 6,
        "added": "2026-05-06",
        "priority": "medium"
      },
      {
        "pattern": "form_ux",
        "count": 7,
        "added": "2026-05-06",
        "priority": "medium"
      },
      {
        "pattern": "realtime_ux",
        "count": 5,
        "added": "2026-05-06",
        "priority": "medium"
      }
    ]
  },
  "history": [
    {
      "date": "2026-03-07",
      "total_merged": 101,
      "total_closed": 73,
      "categories_blocked": [],
      "categories_boosted": []
    },
    {
      "date": "2026-03-08",
      "total_merged": 109,
      "total_closed": 78,
      "categories_blocked": [],
      "categories_boosted": []
    },
    {
      "date": "2026-03-10",
      "total_merged": 112,
      "total_closed": 89,
      "categories_blocked": [],
      "categories_boosted": []
    },
    {
      "date": "2026-03-11",
      "total_merged": 119,
      "total_closed": 95,
      "categories_blocked": [],
      "categories_boosted": []
    },
    {
      "date": "2026-03-13",
      "total_merged": 119,
      "total_closed": 119,
      "categories_blocked": [],
      "categories_boosted": []
    },
    {
      "date": "2026-03-14",
      "total_merged": 119,
      "total_closed": 136,
      "categories_blocked": [],
      "categories_boosted": []
    },
    {
      "date": "2026-03-15",
      "total_merged": 119,
      "total_closed": 142,
      "categories_blocked": [],
      "categories_boosted": []
    },
    {
      "date": "2026-03-17",
      "total_merged": 127,
      "total_closed": 159,
      "categories_blocked": [],
      "categories_boosted": []
    },
    {
      "date": "2026-03-18",
      "total_merged": 135,
      "total_closed": 160,
      "categories_blocked": [],
      "categories_boosted": []
    },
    {
      "date": "2026-03-19",
      "total_merged": 140,
      "total_closed": 160,
      "categories_blocked": [],
      "categories_boosted": []
    },
    {
      "date": "2026-03-20",
      "total_merged": 146,
      "total_closed": 166,
      "categories_blocked": [],
      "categories_boosted": []
    },
    {
      "date": "2026-03-21",
      "total_merged": 153,
      "total_closed": 175,
      "categories_blocked": [],
      "categories_boosted": []
    },
    {
      "date": "2026-03-22",
      "total_merged": 153,
      "total_closed": 182,
      "categories_blocked": [],
      "categories_boosted": []
    },
    {
      "date": "2026-03-23",
      "total_merged": 153,
      "total_closed": 197,
      "categories_blocked": [],
      "categories_boosted": []
    },
    {
      "date": "2026-03-24",
      "total_merged": 158,
      "total_closed": 206,
      "categories_blocked": [],
      "categories_boosted": []
    },
    {
      "date": "2026-03-25",
      "total_merged": 188,
      "total_closed": 222,
      "categories_blocked": [],
      "categories_boosted": []
    },
    {
      "date": "2026-03-26",
      "total_merged": 206,
      "total_closed": 225,
      "categories_blocked": [],
      "categories_boosted": []
    },
    {
      "date": "2026-03-27",
      "total_merged": 206,
      "total_closed": 227,
      "categories_blocked": [],
      "categories_boosted": []
    },
    {
      "date": "2026-03-28",
      "total_merged": 210,
      "total_closed": 228,
      "categories_blocked": [],
      "categories_boosted": []
    },
    {
      "date": "2026-03-29",
      "total_merged": 219,
      "total_closed": 228,
      "categories_blocked": [],
      "categories_boosted": []
    },
    {
      "date": "2026-03-30",
      "total_merged": 110,
      "total_closed": 90,
      "categories_blocked": [],
      "categories_boosted": []
    },
    {
      "date": "2026-04-01",
      "total_merged": 123,
      "total_closed": 93,
      "categories_blocked": [],
      "categories_boosted": []
    },
    {
      "date": "2026-04-02",
      "total_merged": 126,
      "total_closed": 97,
      "categories_blocked": [],
      "categories_boosted": []
    },
    {
      "date": "2026-04-03",
      "total_merged": 131,
      "total_closed": 97,
      "categories_blocked": [],
      "categories_boosted": []
    },
    {
      "date": "2026-04-04",
      "total_merged": 131,
      "total_closed": 132,
      "categories_blocked": [],
      "categories_boosted": []
    },
    {
      "date": "2026-04-05",
      "total_merged": 131,
      "total_closed": 178,
      "categories_blocked": [
        "operator",
        "sre"
      ],
      "categories_boosted": []
    },
    {
      "date": "2026-04-06",
      "total_merged": 131,
      "total_closed": 228,
      "categories_blocked": [
        "operator",
        "sre"
      ],
      "categories_boosted": []
    },
    {
      "date": "2026-04-07",
      "total_merged": 131,
      "total_closed": 278,
      "categories_blocked": [
        "operator",
        "sre"
      ],
      "categories_boosted": []
    },
    {
      "date": "2026-04-08",
      "total_merged": 131,
      "total_closed": 288,
      "categories_blocked": [
        "operator",
        "sre"
      ],
      "categories_boosted": []
    },
    {
      "date": "2026-04-13",
      "total_merged": 131,
      "total_closed": 289,
      "categories_blocked": [
        "operator",
        "sre"
      ],
      "categories_boosted": []
    }
  ],
  "rotation_weights": {
    "performance": 0.71,
    "security": 0.63,
    "a11y": 0.93,
    "operator": 0,
    "sre": 0,
    "features": 0.41,
    "resilience": 0.62,
    "consistency": 0.68
  },
  "max_issues_override": 2,
  "pr_guidance": "Keep changes under 50 lines (size S) for best acceptance rate. Split larger fixes into multiple PRs."
}
